Metadata-Version: 2.4
Name: faker-healthcare-provider
Version: 2.1.0
Summary: Generate realistic healthcare test data in 6 languages (en, es, pt, zh, fr, de): 150+ diseases with correlated ICD-10 codes, medications, symptoms, and more
Author-email: Rodrigo Nogueira <rodrigo.b.nogueira@gmail.com>
License: MIT
Project-URL: Homepage, https://github.com/rodrigobnogueira/faker-healthcare
Project-URL: Repository, https://github.com/rodrigobnogueira/faker-healthcare
Keywords: faker,healthcare,medical,icd10,fake-data,testing,multilingual,i18n,localization
Classifier: Development Status :: 4 - Beta
Classifier: Intended Audience :: Developers
Classifier: License :: OSI Approved :: MIT License
Classifier: Programming Language :: Python :: 3
Classifier: Programming Language :: Python :: 3.10
Classifier: Programming Language :: Python :: 3.11
Classifier: Programming Language :: Python :: 3.12
Classifier: Programming Language :: Python :: 3.13
Requires-Python: >=3.10
License-File: LICENSE
Requires-Dist: faker>=18.0.0
Provides-Extra: dev
Requires-Dist: pytest; extra == "dev"
Requires-Dist: ruff; extra == "dev"
Requires-Dist: mypy; extra == "dev"
Requires-Dist: pre-commit; extra == "dev"
Dynamic: license-file
